fastapi_auth0/__init__.py
fastapi_auth0/auth.py
fastapi_auth0/py.typed
fastapi_auth0-0.5.0.dist-info/LICENSE.txt
fastapi_auth0-0.5.0.dist-info/METADATA
fastapi_auth0-0.5.0.dist-info/WHEEL
fastapi_auth0-0.5.0.dist-info/top_level.txt
fastapi_auth0-0.5.0.dist-info/RECORD
