Metadata-Version: 2.1
Name: fastapi-auth0
Version: 0.5.0
Summary: Easy auth0.com integration for FastAPI
Home-page: https://github.com/dorinclisu/fastapi-auth0
Author: Dorin Clisu
License: MIT
Platform: UNKNOWN
Requires-Python: >=3.7
License-File: LICENSE.txt
